xaal/__init__.py
xaal/dashboard/__init__.py
xaal/dashboard/__main__.py
xaal/dashboard/app.py
xaal/dashboard/core/__init__.py
xaal/dashboard/core/json.py
xaal/dashboard/core/sio.py
xaal/dashboard/core/xaal_core.py
xaal/dashboard/pages/__init__.py
xaal/dashboard/pages/base.py
xaal/dashboard/pages/default.py
xaal/dashboard/pages/warp10.py
xaal/dashboard/static/latency.html
xaal/dashboard/static/manifest.json
xaal/dashboard/static/css/btns.css
xaal/dashboard/static/css/site.css
xaal/dashboard/static/css/style.old.css
xaal/dashboard/static/fonts/EncodeSans-Regular.ttf
xaal/dashboard/static/fonts/glyphicons-halflings-regular.eot
xaal/dashboard/static/fonts/glyphicons-halflings-regular.svg
xaal/dashboard/static/fonts/glyphicons-halflings-regular.ttf
xaal/dashboard/static/fonts/glyphicons-halflings-regular.woff
xaal/dashboard/static/fonts/glyphicons-halflings-regular.woff2
xaal/dashboard/static/fonts/sansation_light.woff
xaal/dashboard/static/imgs/bg1.jpg
xaal/dashboard/static/imgs/bg3.jpg
xaal/dashboard/static/imgs/bg5.jpg
xaal/dashboard/static/imgs/favicon.ico
xaal/dashboard/static/imgs/launcher-icon-4x.png
xaal/dashboard/static/js/riot+compiler.min.js
xaal/dashboard/static/js/site.js
xaal/dashboard/static/js/socket.io.min.js
xaal/dashboard/static/js/socket.io.min.js.map
xaal/dashboard/static/js/sorttable.js
xaal/dashboard/static/tags/barometer.tag
xaal/dashboard/static/tags/clock.tag
xaal/dashboard/static/tags/co2meter.tag
xaal/dashboard/static/tags/contact.tag
xaal/dashboard/static/tags/debug_btn.tag
xaal/dashboard/static/tags/door.tag
xaal/dashboard/static/tags/fall.tag
xaal/dashboard/static/tags/generic_attrs.tag
xaal/dashboard/static/tags/hygrometer.tag
xaal/dashboard/static/tags/lamp.tag
xaal/dashboard/static/tags/lamp_color.tag
xaal/dashboard/static/tags/lightgauge.tag
xaal/dashboard/static/tags/luxmeter.tag
xaal/dashboard/static/tags/motion.tag
xaal/dashboard/static/tags/powermeter.tag
xaal/dashboard/static/tags/powerrelay.tag
xaal_dashboard-0.4.2.dist-info/METADATA
xaal_dashboard-0.4.2.dist-info/WHEEL
xaal_dashboard-0.4.2.dist-info/top_level.txt
xaal_dashboard-0.4.2.dist-info/RECORD
