Metadata-Version: 2.4
Name: xaal.dashboard
Version: 0.4.2
Summary: xAAL Dashboard
Author-email: Jerome Kerdreux <Jerome.Kerdreux@imt-atlantique.fr>
License-Expression: GPL-3.0-or-later
Project-URL: Homepage, https://recherche.imt-atlantique.fr/xaal/
Project-URL: Documentation, https://gitlab.imt-atlantique.fr/xaal/code/python/-/blob/main/apps/dashboard/README.rst
Project-URL: Source, https://gitlab.imt-atlantique.fr/xaal/code/python/-/tree/main/apps/dashboard
Keywords: xaal,socketio,html,dashboard
Classifier: Programming Language :: Python
Classifier: Topic :: Home Automation
Requires-Dist: xaal.lib
Requires-Dist: xaal.monitor
Requires-Dist: python-rapidjson
Requires-Dist: bottle
Requires-Dist: gevent
Requires-Dist: gevent-websocket
Requires-Dist: python-engineio
Requires-Dist: python-socketio
Requires-Dist: mako
Requires-Dist: requests
